ndtamr/AMR.py
ndtamr/Data.py
ndtamr/NDTree.py
ndtamr/Vis.py
ndtamr/__init__.py
ndtamr-0.3.dist-info/DESCRIPTION.rst
ndtamr-0.3.dist-info/METADATA
ndtamr-0.3.dist-info/RECORD
ndtamr-0.3.dist-info/WHEEL
ndtamr-0.3.dist-info/metadata.json
ndtamr-0.3.dist-info/top_level.txt
